{
  "key": "_br_340056",
  "codes": {
    "icao": null,
    "iata": null,
    "gps": "SNKZ",
    "local": "MT0610"
  },
  "name": "Fazenda São Marcos Airport",
  "type": "small_airport",
  "status": "open",
  "location": {
    "latitude": -15.467652,
    "longitude": -59.943735,
    "elevation_ft": 722,
    "iso_country": "BR",
    "iso_region": "BR-MT",
    "municipality": "Vila Bela da Santíssima Trindade"
  },
  "keywords": [
    "BR-1359"
  ],
  "metadata": {
    "created": "2026-06-21",
    "updated": "2026-06-21",
    "sources": [
      "ourairports"
    ],
    "curated": false,
    "source_id": 340056
  }
}
