{
  "key": "_au_314878",
  "codes": {
    "icao": null,
    "iata": null,
    "gps": null,
    "local": "OZHBQ"
  },
  "name": "Dululu Helicopter Landing Site",
  "type": "heliport",
  "status": "open",
  "location": {
    "latitude": -23.8479,
    "longitude": 150.2625,
    "elevation_ft": 428,
    "iso_country": "AU",
    "iso_region": "AU-QLD",
    "municipality": "Dululu"
  },
  "keywords": [
    "AU-0091"
  ],
  "metadata": {
    "created": "2026-06-21",
    "updated": "2026-06-21",
    "sources": [
      "ourairports"
    ],
    "curated": false,
    "source_id": 314878
  }
}
