{
  "key": "_br_36280",
  "codes": {
    "icao": null,
    "iata": null,
    "gps": "SITX",
    "local": null
  },
  "name": "Fazenda Chapéu de Pano Airport",
  "type": "small_airport",
  "status": "open",
  "location": {
    "latitude": -19.774445,
    "longitude": -55.521667,
    "elevation_ft": 519,
    "iso_country": "BR",
    "iso_region": "BR-MS",
    "municipality": "Aquidauana"
  },
  "keywords": [
    "SITX"
  ],
  "metadata": {
    "created": "2026-06-21",
    "updated": "2026-06-21",
    "sources": [
      "ourairports"
    ],
    "curated": false,
    "source_id": 36280
  }
}
