{
  "key": "_br_36943",
  "codes": {
    "icao": null,
    "iata": null,
    "gps": null,
    "local": null
  },
  "name": "Fazenda Santa Inês Airport",
  "type": "small_airport",
  "status": "open",
  "location": {
    "latitude": -14.661772,
    "longitude": -55.384305,
    "elevation_ft": 1330,
    "iso_country": "BR",
    "iso_region": "BR-MT",
    "municipality": "Nova Brasilândia"
  },
  "keywords": [
    "SJWH",
    "BR-2733"
  ],
  "metadata": {
    "created": "2026-06-21",
    "updated": "2026-06-21",
    "sources": [
      "ourairports"
    ],
    "curated": false,
    "source_id": 36943
  }
}
