{
  "key": "_ca_321385",
  "codes": {
    "icao": null,
    "iata": null,
    "gps": null,
    "local": null
  },
  "name": "Geraldton Water Aerodrome",
  "type": "closed",
  "status": "closed",
  "location": {
    "latitude": 49.6963,
    "longitude": -86.86,
    "elevation_ft": 1086,
    "iso_country": "CA",
    "iso_region": "CA-ON",
    "municipality": "Geraldton"
  },
  "keywords": [
    "NA6",
    "CA-0675"
  ],
  "metadata": {
    "created": "2026-06-21",
    "updated": "2026-06-21",
    "sources": [
      "ourairports"
    ],
    "curated": false,
    "source_id": 321385
  }
}
