{
  "key": "_ph_594270",
  "codes": {
    "icao": null,
    "iata": null,
    "gps": null,
    "local": null
  },
  "name": "Padada Heliport",
  "type": "heliport",
  "status": "open",
  "location": {
    "latitude": 6.69916,
    "longitude": 125.33645,
    "elevation_ft": 36,
    "iso_country": "PH",
    "iso_region": "PH-DAS",
    "municipality": "Hagonoy"
  },
  "keywords": [
    "PH-0712"
  ],
  "metadata": {
    "created": "2026-06-21",
    "updated": "2026-06-21",
    "sources": [
      "ourairports"
    ],
    "curated": false,
    "source_id": 594270
  }
}
