{
  "key": "_ph_337366",
  "codes": {
    "icao": null,
    "iata": null,
    "gps": null,
    "local": null
  },
  "name": "Air Juan Boracay Seaplane Terminal",
  "type": "closed",
  "status": "closed",
  "location": {
    "latitude": 11.97444,
    "longitude": 121.91277,
    "elevation_ft": 0,
    "iso_country": "PH",
    "iso_region": "PH-AKL",
    "municipality": "Malay"
  },
  "keywords": [
    "PH-0208"
  ],
  "metadata": {
    "created": "2026-06-21",
    "updated": "2026-06-21",
    "sources": [
      "ourairports"
    ],
    "curated": false,
    "source_id": 337366
  }
}
