{
  "key": "_us_17246",
  "codes": {
    "icao": null,
    "iata": null,
    "gps": "FA56",
    "local": "FA56"
  },
  "name": "North Florida Regional Medical Center Heliport",
  "type": "heliport",
  "status": "open",
  "location": {
    "latitude": 29.661501,
    "longitude": -82.412102,
    "elevation_ft": 143,
    "iso_country": "US",
    "iso_region": "US-FL",
    "municipality": "Gainesville"
  },
  "keywords": [],
  "metadata": {
    "created": "2026-06-21",
    "updated": "2026-06-21",
    "sources": [
      "ourairports"
    ],
    "curated": false,
    "source_id": 17246
  }
}
