{
  "key": "_us_24834",
  "codes": {
    "icao": null,
    "iata": null,
    "gps": "TE26",
    "local": "TE26"
  },
  "name": "Arrow 'S' Ranch Airport",
  "type": "small_airport",
  "status": "open",
  "location": {
    "latitude": 28.7836,
    "longitude": -98.349998,
    "elevation_ft": 275,
    "iso_country": "US",
    "iso_region": "US-TX",
    "municipality": "Campbellton"
  },
  "keywords": [],
  "metadata": {
    "created": "2026-06-21",
    "updated": "2026-06-21",
    "sources": [
      "ourairports"
    ],
    "curated": false,
    "source_id": 24834
  }
}
