{
  "key": "_us_24495",
  "codes": {
    "icao": null,
    "iata": null,
    "gps": "SC97",
    "local": "SC97"
  },
  "name": "Riverbend Airpark",
  "type": "small_airport",
  "status": "open",
  "location": {
    "latitude": 34.7267,
    "longitude": -82.339699,
    "elevation_ft": 920,
    "iso_country": "US",
    "iso_region": "US-SC",
    "municipality": "Mauldin"
  },
  "keywords": [],
  "metadata": {
    "created": "2026-06-21",
    "updated": "2026-06-21",
    "sources": [
      "ourairports"
    ],
    "curated": false,
    "source_id": 24495
  }
}
