{
  "key": "_br_430391",
  "codes": {
    "icao": null,
    "iata": null,
    "gps": "SJ3D",
    "local": "BA0417"
  },
  "name": "Fazenda Sinimbu Airport",
  "type": "small_airport",
  "status": "open",
  "location": {
    "latitude": -13.86631,
    "longitude": -45.165353,
    "elevation_ft": 2523,
    "iso_country": "BR",
    "iso_region": "BR-BA",
    "municipality": "Jaborandi"
  },
  "keywords": [],
  "metadata": {
    "created": "2026-06-21",
    "updated": "2026-06-21",
    "sources": [
      "ourairports"
    ],
    "curated": false,
    "source_id": 430391
  }
}
