{
  "key": "_us_11430",
  "codes": {
    "icao": null,
    "iata": null,
    "gps": null,
    "local": null
  },
  "name": "Southwire Heliport",
  "type": "closed",
  "status": "closed",
  "location": {
    "latitude": 33.566562,
    "longitude": -85.070522,
    "elevation_ft": 1094,
    "iso_country": "US",
    "iso_region": "US-GA",
    "municipality": "Carrollton"
  },
  "keywords": [
    "4GA5",
    "US-10198"
  ],
  "metadata": {
    "created": "2026-06-21",
    "updated": "2026-06-21",
    "sources": [
      "ourairports"
    ],
    "curated": false,
    "source_id": 11430
  }
}
