{
  "key": "_us_11913",
  "codes": {
    "icao": null,
    "iata": null,
    "gps": "52II",
    "local": "52II"
  },
  "name": "Marshall County Heliport",
  "type": "heliport",
  "status": "open",
  "location": {
    "latitude": 41.338902,
    "longitude": -86.263298,
    "elevation_ft": 824,
    "iso_country": "US",
    "iso_region": "US-IN",
    "municipality": "Plymouth"
  },
  "keywords": [],
  "metadata": {
    "created": "2026-06-21",
    "updated": "2026-06-21",
    "sources": [
      "ourairports"
    ],
    "curated": false,
    "source_id": 11913
  }
}
