{
  "key": "_us_11424",
  "codes": {
    "icao": null,
    "iata": null,
    "gps": "K4G7",
    "local": "4G7"
  },
  "name": "Fairmont Municipal Airport Frankman Field",
  "type": "small_airport",
  "status": "open",
  "location": {
    "latitude": 39.4482,
    "longitude": -80.167,
    "elevation_ft": 1029,
    "iso_country": "US",
    "iso_region": "US-WV",
    "municipality": "Fairmont"
  },
  "keywords": [],
  "wikipedia": "https://en.wikipedia.org/wiki/Fairmont_Municipal_Airport_(West_Virginia)",
  "metadata": {
    "created": "2026-06-21",
    "updated": "2026-06-21",
    "sources": [
      "ourairports"
    ],
    "curated": false,
    "source_id": 11424
  }
}
