{
  "key": "_ke_42538",
  "codes": {
    "icao": null,
    "iata": null,
    "gps": null,
    "local": null
  },
  "name": "Embakasi Airport",
  "type": "closed",
  "status": "closed",
  "location": {
    "latitude": -1.298219,
    "longitude": 36.915546,
    "elevation_ft": 5357,
    "iso_country": "KE",
    "iso_region": "KE-47",
    "municipality": "Embakasi"
  },
  "keywords": [
    "HKSA",
    "KE-7004"
  ],
  "metadata": {
    "created": "2026-06-21",
    "updated": "2026-06-21",
    "sources": [
      "ourairports"
    ],
    "curated": false,
    "source_id": 42538
  }
}
