{
  "key": "_de_514195",
  "codes": {
    "icao": null,
    "iata": null,
    "gps": null,
    "local": null
  },
  "name": "Enghausen Heliport",
  "type": "heliport",
  "status": "open",
  "location": {
    "latitude": 48.53653,
    "longitude": 11.90451,
    "elevation_ft": 1483,
    "iso_country": "DE",
    "iso_region": "DE-BY",
    "municipality": "Mauern"
  },
  "keywords": [
    "DE-0557"
  ],
  "metadata": {
    "created": "2026-06-21",
    "updated": "2026-06-21",
    "sources": [
      "ourairports"
    ],
    "curated": false,
    "source_id": 514195
  }
}
