{
  "key": "_bw_317562",
  "codes": {
    "icao": null,
    "iata": null,
    "gps": "FBGD",
    "local": null
  },
  "name": "Gundingwa Airport",
  "type": "small_airport",
  "status": "open",
  "location": {
    "latitude": -18.61649,
    "longitude": 22.915932,
    "elevation_ft": 3165,
    "iso_country": "BW",
    "iso_region": "BW-NW",
    "municipality": "Gundingwa"
  },
  "keywords": [
    "FB20",
    "Gudigwa",
    "Gudingwa"
  ],
  "metadata": {
    "created": "2026-06-21",
    "updated": "2026-06-21",
    "sources": [
      "ourairports"
    ],
    "curated": false,
    "source_id": 317562
  }
}
