{
  "key": "_tw_325273",
  "codes": {
    "icao": null,
    "iata": null,
    "gps": null,
    "local": null
  },
  "name": "Hualien Hospital Heliport",
  "type": "heliport",
  "status": "open",
  "location": {
    "latitude": 23.978511,
    "longitude": 121.611904,
    "elevation_ft": 0,
    "iso_country": "TW",
    "iso_region": "TW-HUA",
    "municipality": "Hualien"
  },
  "keywords": [
    "Hulien Hospital",
    "胡聯醫院直升機場",
    "TW-0012"
  ],
  "metadata": {
    "created": "2026-06-21",
    "updated": "2026-06-21",
    "sources": [
      "ourairports"
    ],
    "curated": false,
    "source_id": 325273
  }
}
