{
  "key": "_ca_511147",
  "codes": {
    "icao": null,
    "iata": null,
    "gps": null,
    "local": null
  },
  "name": "Saint-Cyprien Airport",
  "type": "small_airport",
  "status": "open",
  "location": {
    "latitude": 46.34576,
    "longitude": -70.19539,
    "elevation_ft": 1225,
    "iso_country": "CA",
    "iso_region": "CA-QC",
    "municipality": "Saint-Cyprien"
  },
  "keywords": [
    "CA-0877"
  ],
  "metadata": {
    "created": "2026-06-21",
    "updated": "2026-06-21",
    "sources": [
      "ourairports"
    ],
    "curated": false,
    "source_id": 511147
  }
}
