{
  "key": "_gb_307949",
  "codes": {
    "icao": null,
    "iata": null,
    "gps": null,
    "local": null
  },
  "name": "RAF Birch",
  "type": "closed",
  "status": "closed",
  "location": {
    "latitude": 51.8425,
    "longitude": 0.780556,
    "elevation_ft": 0,
    "iso_country": "GB",
    "iso_region": "GB-ENG",
    "municipality": "Colchester, Essex"
  },
  "keywords": [
    "Birch Airfield",
    "GB-0118"
  ],
  "wikipedia": "https://en.wikipedia.org/wiki/RAF_Birch",
  "metadata": {
    "created": "2026-06-21",
    "updated": "2026-06-21",
    "sources": [
      "ourairports"
    ],
    "curated": false,
    "source_id": 307949
  }
}
