{
  "key": "_ar_608232",
  "codes": {
    "icao": null,
    "iata": null,
    "gps": null,
    "local": "2492"
  },
  "name": "L.A.D. Estancia 10 de Julio Airport",
  "type": "small_airport",
  "status": "open",
  "location": {
    "latitude": -33.403042,
    "longitude": -63.507107,
    "elevation_ft": 562,
    "iso_country": "AR",
    "iso_region": "AR-X",
    "municipality": "Los Cisnes"
  },
  "keywords": [
    "AR-0776"
  ],
  "metadata": {
    "created": "2026-06-21",
    "updated": "2026-06-21",
    "sources": [
      "ourairports"
    ],
    "curated": false,
    "source_id": 608232
  }
}
