{
  "key": "_fr_557518",
  "codes": {
    "icao": null,
    "iata": null,
    "gps": null,
    "local": null
  },
  "name": "Carnières",
  "type": "heliport",
  "status": "open",
  "location": {
    "latitude": 50.172315,
    "longitude": 3.350004,
    "elevation_ft": 0,
    "iso_country": "FR",
    "iso_region": "FR-HDF",
    "municipality": "Carnières"
  },
  "keywords": [
    "FR-1201"
  ],
  "metadata": {
    "created": "2026-06-21",
    "updated": "2026-06-21",
    "sources": [
      "ourairports"
    ],
    "curated": false,
    "source_id": 557518
  }
}
