{
  "key": "_us_12446",
  "codes": {
    "icao": null,
    "iata": null,
    "gps": "5L6",
    "local": "5L6"
  },
  "name": "Wasilla Lake Seaplane Base",
  "type": "seaplane_base",
  "status": "open",
  "location": {
    "latitude": 61.586399,
    "longitude": -149.408005,
    "elevation_ft": 330,
    "iso_country": "US",
    "iso_region": "US-AK",
    "municipality": "Wasilla"
  },
  "keywords": [],
  "metadata": {
    "created": "2026-06-21",
    "updated": "2026-06-21",
    "sources": [
      "ourairports"
    ],
    "curated": false,
    "source_id": 12446
  }
}
