{
  "key": "_us_12479",
  "codes": {
    "icao": null,
    "iata": null,
    "gps": "5MD1",
    "local": "5MD1"
  },
  "name": "Brooklandville Heliport",
  "type": "heliport",
  "status": "open",
  "location": {
    "latitude": 39.416698,
    "longitude": -76.677803,
    "elevation_ft": 312,
    "iso_country": "US",
    "iso_region": "US-MD",
    "municipality": "Brooklandville"
  },
  "keywords": [],
  "metadata": {
    "created": "2026-06-21",
    "updated": "2026-06-21",
    "sources": [
      "ourairports"
    ],
    "curated": false,
    "source_id": 12479
  }
}
