{
  "key": "_us_506509",
  "codes": {
    "icao": null,
    "iata": null,
    "gps": null,
    "local": null
  },
  "name": "Frank A Tracy Generating Station Heliport",
  "type": "heliport",
  "status": "open",
  "location": {
    "latitude": 39.56161,
    "longitude": -119.52191,
    "elevation_ft": 4284,
    "iso_country": "US",
    "iso_region": "US-NV",
    "municipality": "Sparks"
  },
  "keywords": [
    "US-7543"
  ],
  "metadata": {
    "created": "2026-06-21",
    "updated": "2026-06-21",
    "sources": [
      "ourairports"
    ],
    "curated": false,
    "source_id": 506509
  }
}
