{
  "key": "_ca_01250",
  "codes": {
    "icao": null,
    "iata": null,
    "gps": null,
    "local": null
  },
  "name": "Wilkie Airport",
  "type": "closed",
  "status": "closed",
  "location": {
    "latitude": 52.403099,
    "longitude": -108.720001,
    "elevation_ft": 2149,
    "iso_country": "CA",
    "iso_region": "CA-SK",
    "municipality": "Wilkie"
  },
  "keywords": [
    "KW7",
    "CKW7",
    "CA-1063"
  ],
  "wikipedia": "https://en.wikipedia.org/wiki/Wilkie_Airport",
  "metadata": {
    "created": "2026-06-21",
    "updated": "2026-06-21",
    "sources": [
      "ourairports"
    ],
    "curated": false,
    "source_id": 1250
  }
}
