{
  "key": "_sl_30799",
  "codes": {
    "icao": null,
    "iata": null,
    "gps": null,
    "local": null
  },
  "name": "Sherbro International Airport",
  "type": "closed",
  "status": "closed",
  "location": {
    "latitude": 7.53242,
    "longitude": -12.5189,
    "elevation_ft": 14,
    "iso_country": "SL",
    "iso_region": "SL-S",
    "municipality": "Bonthe"
  },
  "keywords": [
    "Bonthe Airport",
    "GFBN",
    "BTE",
    "SL-0004"
  ],
  "wikipedia": "https://en.wikipedia.org/wiki/Sherbro_International_Airport",
  "metadata": {
    "created": "2026-06-21",
    "updated": "2026-06-21",
    "sources": [
      "ourairports"
    ],
    "curated": false,
    "source_id": 30799
  }
}
