{
  "key": "_cd_31336",
  "codes": {
    "icao": null,
    "iata": null,
    "gps": null,
    "local": null
  },
  "name": "Kenge Airport",
  "type": "closed",
  "status": "closed",
  "location": {
    "latitude": -4.837882,
    "longitude": 17.029452,
    "elevation_ft": 1808,
    "iso_country": "CD",
    "iso_region": "CD-KG",
    "municipality": "Kenge"
  },
  "keywords": [
    "FZCS"
  ],
  "wikipedia": "https://en.wikipedia.org/wiki/Kenge_Airport",
  "metadata": {
    "created": "2026-06-21",
    "updated": "2026-06-21",
    "sources": [
      "ourairports"
    ],
    "curated": false,
    "source_id": 31336
  }
}
