{
  "key": "_cn_351129",
  "codes": {
    "icao": null,
    "iata": null,
    "gps": null,
    "local": null
  },
  "name": "Guilin Gaotian Heliport",
  "type": "heliport",
  "status": "open",
  "location": {
    "latitude": 24.71781,
    "longitude": 110.45589,
    "elevation_ft": 459,
    "iso_country": "CN",
    "iso_region": "CN-45",
    "municipality": "Guilin (Yangshuo)"
  },
  "keywords": [
    "CN-0286"
  ],
  "metadata": {
    "created": "2026-06-21",
    "updated": "2026-06-21",
    "sources": [
      "ourairports"
    ],
    "curated": false,
    "source_id": 351129
  }
}
