{
  "key": "_pt_326677",
  "codes": {
    "icao": null,
    "iata": null,
    "gps": null,
    "local": null
  },
  "name": "Pista de Aguas de Moura",
  "type": "small_airport",
  "status": "open",
  "location": {
    "latitude": 38.579004,
    "longitude": -8.696119,
    "elevation_ft": 0,
    "iso_country": "PT",
    "iso_region": "PT-15",
    "municipality": "Palmela"
  },
  "keywords": [
    "PT-0064"
  ],
  "metadata": {
    "created": "2026-06-21",
    "updated": "2026-06-21",
    "sources": [
      "ourairports"
    ],
    "curated": false,
    "source_id": 326677
  }
}
