{
  "key": "zbsn",
  "codes": {
    "icao": "ZBSN",
    "iata": "TVS",
    "gps": "ZBSN",
    "local": null
  },
  "name": "Tangshan Sannühe Airport",
  "type": "small_airport",
  "status": "open",
  "location": {
    "latitude": 39.7178,
    "longitude": 118.002625,
    "elevation_ft": 50,
    "iso_country": "CN",
    "iso_region": "CN-13",
    "municipality": "Tangshan (Fengrun)"
  },
  "keywords": [
    "Tangshan Air Base",
    "唐山三女河机场"
  ],
  "wikipedia": "https://en.wikipedia.org/wiki/Tangshan_Sann%C3%BChe_Airport",
  "metadata": {
    "created": "2026-06-21",
    "updated": "2026-06-21",
    "sources": [
      "ourairports"
    ],
    "curated": false,
    "source_id": 43975
  }
}
