{
  "key": "_us_329637",
  "codes": {
    "icao": null,
    "iata": null,
    "gps": "76NR",
    "local": "76NR"
  },
  "name": "Pathfinder Field",
  "type": "small_airport",
  "status": "open",
  "location": {
    "latitude": 34.97417,
    "longitude": -79.074545,
    "elevation_ft": 217,
    "iso_country": "US",
    "iso_region": "US-NC",
    "municipality": "Raeford"
  },
  "keywords": [
    "Allens Airport",
    "Rockfish",
    "US-1003"
  ],
  "metadata": {
    "created": "2026-06-21",
    "updated": "2026-06-21",
    "sources": [
      "ourairports"
    ],
    "curated": false,
    "source_id": 329637
  }
}
