{
  "key": "_us_325821",
  "codes": {
    "icao": null,
    "iata": null,
    "gps": "PA06",
    "local": "PA06"
  },
  "name": "Pacer Place Heliport",
  "type": "heliport",
  "status": "open",
  "location": {
    "latitude": 61.129694,
    "longitude": -149.795918,
    "elevation_ft": 367,
    "iso_country": "US",
    "iso_region": "US-AK",
    "municipality": "Anchorage"
  },
  "keywords": [],
  "metadata": {
    "created": "2026-06-21",
    "updated": "2026-06-21",
    "sources": [
      "ourairports"
    ],
    "curated": false,
    "source_id": 325821
  }
}
