{
  "key": "_ca_39896",
  "codes": {
    "icao": null,
    "iata": null,
    "gps": null,
    "local": null
  },
  "name": "Mountain River Airport",
  "type": "closed",
  "status": "closed",
  "location": {
    "latitude": 65.681531,
    "longitude": -128.826921,
    "elevation_ft": 150,
    "iso_country": "CA",
    "iso_region": "CA-NT",
    "municipality": null
  },
  "keywords": [
    "EE2",
    "CA-0250"
  ],
  "metadata": {
    "created": "2026-06-21",
    "updated": "2026-06-21",
    "sources": [
      "ourairports"
    ],
    "curated": false,
    "source_id": 39896
  }
}
