{
  "key": "_ca_39721",
  "codes": {
    "icao": null,
    "iata": null,
    "gps": null,
    "local": null
  },
  "name": "Terra Mining Airport",
  "type": "closed",
  "status": "closed",
  "location": {
    "latitude": 65.609152,
    "longitude": -118.141592,
    "elevation_ft": 550,
    "iso_country": "CA",
    "iso_region": "CA-NT",
    "municipality": "Camsell River"
  },
  "keywords": [
    "FS3",
    "CA-0075"
  ],
  "metadata": {
    "created": "2026-06-21",
    "updated": "2026-06-21",
    "sources": [
      "ourairports"
    ],
    "curated": false,
    "source_id": 39721
  }
}
