{
  "key": "_us_23367",
  "codes": {
    "icao": null,
    "iata": null,
    "gps": "NV67",
    "local": "NV67"
  },
  "name": "Pilot Creek Ranches Airport",
  "type": "small_airport",
  "status": "open",
  "location": {
    "latitude": 41.115799,
    "longitude": -114.113998,
    "elevation_ft": 4980,
    "iso_country": "US",
    "iso_region": "US-NV",
    "municipality": "Montello"
  },
  "keywords": [],
  "metadata": {
    "created": "2026-06-21",
    "updated": "2026-06-21",
    "sources": [
      "ourairports"
    ],
    "curated": false,
    "source_id": 23367
  }
}
