{
  "key": "_us_19666",
  "codes": {
    "icao": null,
    "iata": null,
    "gps": "KDUX",
    "local": "DUX"
  },
  "name": "Moore County Airport",
  "type": "small_airport",
  "status": "open",
  "location": {
    "latitude": 35.857899,
    "longitude": -102.013,
    "elevation_ft": 3705,
    "iso_country": "US",
    "iso_region": "US-TX",
    "municipality": "Dumas"
  },
  "keywords": [],
  "wikipedia": "https://en.wikipedia.org/wiki/Moore_County_Airport_(Texas)",
  "metadata": {
    "created": "2026-06-21",
    "updated": "2026-06-21",
    "sources": [
      "ourairports"
    ],
    "curated": false,
    "source_id": 19666
  }
}
