{
  "icao": null,
  "iata": null,
  "name": "Middle Sedge Island Heliport",
  "type": "heliport",
  "status": "open",
  "location": {
    "latitude": 40.000099182128906,
    "longitude": -74.0801010131836,
    "elevation_ft": 5,
    "continent": "NA",
    "iso_country": "US",
    "iso_region": "US-NJ",
    "municipality": "Toms River"
  },
  "scheduled_service": false,
  "wikipedia": null,
  "keywords": [],
  "runways": [],
  "frequencies": [],
  "metadata": {
    "ourairports_id": 15461,
    "created": "2026-03-06",
    "updated": "2026-03-06",
    "sources": [
      "ourairports",
      "faa"
    ]
  }
}