{
  "icao": null,
  "iata": null,
  "name": "Indian Hill Resort Airport",
  "type": "closed",
  "status": "open",
  "location": {
    "latitude": 47.605598,
    "longitude": -102.105003,
    "elevation_ft": 2010,
    "continent": "NA",
    "iso_country": "US",
    "iso_region": "US-ND",
    "municipality": "Garrison"
  },
  "scheduled_service": false,
  "wikipedia": null,
  "keywords": [
    "ND87"
  ],
  "runways": [],
  "frequencies": [],
  "metadata": {
    "ourairports_id": 22894,
    "created": "2026-03-06",
    "updated": "2026-03-06",
    "sources": [
      "ourairports",
      "faa"
    ]
  }
}