{
  "icao": null,
  "iata": null,
  "name": "Strathmore Field",
  "type": "closed",
  "status": "open",
  "location": {
    "latitude": 36.11303,
    "longitude": -119.12049,
    "elevation_ft": 380,
    "continent": "NA",
    "iso_country": "US",
    "iso_region": "US-CA",
    "municipality": "Porterville"
  },
  "scheduled_service": false,
  "wikipedia": null,
  "keywords": [],
  "runways": [],
  "frequencies": [],
  "metadata": {
    "ourairports_id": 350087,
    "created": "2026-03-06",
    "updated": "2026-03-06",
    "sources": [
      "ourairports",
      "faa"
    ]
  }
}