{
  "icao": null,
  "iata": null,
  "name": "Naval Air Station Albany",
  "type": "closed",
  "status": "open",
  "location": {
    "latitude": 31.595061,
    "longitude": -84.090042,
    "elevation_ft": 217,
    "continent": "NA",
    "iso_country": "US",
    "iso_region": "US-GA",
    "municipality": "Albany"
  },
  "scheduled_service": false,
  "wikipedia": "https://en.wikipedia.org/wiki/Naval_Air_Station_Albany",
  "keywords": [
    "NAB",
    "KNAB",
    "Turner Air Force Base",
    "Turner Field"
  ],
  "runways": [],
  "frequencies": [],
  "metadata": {
    "ourairports_id": 324074,
    "created": "2026-03-06",
    "updated": "2026-03-06",
    "sources": [
      "ourairports",
      "faa"
    ]
  }
}