{
  "icao": null,
  "iata": null,
  "name": "Custer Main Heliport",
  "type": "heliport",
  "status": "open",
  "location": {
    "latitude": 42.33169937133789,
    "longitude": -85.29669952392578,
    "elevation_ft": 883,
    "continent": "NA",
    "iso_country": "US",
    "iso_region": "US-MI",
    "municipality": "Battle Creek"
  },
  "scheduled_service": false,
  "wikipedia": null,
  "keywords": [],
  "runways": [],
  "frequencies": [],
  "metadata": {
    "ourairports_id": 15804,
    "created": "2026-03-06",
    "updated": "2026-03-06",
    "sources": [
      "ourairports",
      "faa"
    ]
  }
}