{
  "icao": null,
  "iata": null,
  "name": "Ainsworth Airport",
  "type": "small_airport",
  "status": "open",
  "location": {
    "latitude": 41.295551,
    "longitude": -91.575012,
    "elevation_ft": 747,
    "continent": "NA",
    "iso_country": "US",
    "iso_region": "US-IA",
    "municipality": "Ainsworth"
  },
  "scheduled_service": false,
  "wikipedia": null,
  "keywords": [],
  "runways": [],
  "frequencies": [],
  "metadata": {
    "ourairports_id": 534723,
    "created": "2026-03-06",
    "updated": "2026-03-06",
    "sources": [
      "ourairports",
      "faa"
    ]
  }
}