{
  "icao": null,
  "iata": null,
  "name": "Stangland Airport",
  "type": "small_airport",
  "status": "open",
  "location": {
    "latitude": 41.315804,
    "longitude": -85.464878,
    "elevation_ft": 924,
    "continent": "NA",
    "iso_country": "US",
    "iso_region": "US-IN",
    "municipality": "Wolflake"
  },
  "scheduled_service": false,
  "wikipedia": null,
  "keywords": [],
  "runways": [],
  "frequencies": [],
  "metadata": {
    "ourairports_id": 12413,
    "created": "2026-03-06",
    "updated": "2026-03-06",
    "sources": [
      "ourairports",
      "faa"
    ]
  }
}