{
  "icao": null,
  "iata": null,
  "name": "Talbott Field",
  "type": "small_airport",
  "status": "open",
  "location": {
    "latitude": 39.333848,
    "longitude": -78.104998,
    "elevation_ft": 755,
    "continent": "NA",
    "iso_country": "US",
    "iso_region": "US-WV",
    "municipality": "Gerrardstown"
  },
  "scheduled_service": false,
  "wikipedia": null,
  "keywords": [],
  "runways": [],
  "frequencies": [],
  "metadata": {
    "ourairports_id": 514500,
    "created": "2026-03-06",
    "updated": "2026-03-06",
    "sources": [
      "ourairports",
      "faa"
    ]
  }
}