{
  "icao": null,
  "iata": null,
  "name": "Owasco Airport",
  "type": "small_airport",
  "status": "open",
  "location": {
    "latitude": 42.736493,
    "longitude": -76.486065,
    "elevation_ft": 1378,
    "continent": "NA",
    "iso_country": "US",
    "iso_region": "US-NY",
    "municipality": "Moravia"
  },
  "scheduled_service": false,
  "wikipedia": null,
  "keywords": [
    "92NK",
    "NY92",
    "Y92"
  ],
  "runways": [],
  "frequencies": [],
  "metadata": {
    "ourairports_id": 23471,
    "created": "2026-03-06",
    "updated": "2026-03-06",
    "sources": [
      "ourairports",
      "faa"
    ]
  }
}