{
  "icao": null,
  "iata": null,
  "name": "Cross Triangle Ranch Airport",
  "type": "small_airport",
  "status": "open",
  "location": {
    "latitude": 30.0104999542,
    "longitude": -98.4253005981,
    "elevation_ft": 1420,
    "continent": "NA",
    "iso_country": "US",
    "iso_region": "US-TX",
    "municipality": "Twin Sisters"
  },
  "scheduled_service": false,
  "wikipedia": null,
  "keywords": [],
  "runways": [
    {
      "id": "17/35",
      "length_ft": 3000,
      "width_ft": 50,
      "surface": "asphalt",
      "lighted": false,
      "closed": false,
      "ends": {
        "low": {
          "ident": "17",
          "latitude": 30.014400482177734,
          "longitude": -98.42610168457031,
          "elevation_ft": 0,
          "heading_true": 170,
          "displaced_threshold_ft": 0
        },
        "high": {
          "ident": "35",
          "latitude": 30.006399154663086,
          "longitude": -98.42440032958984,
          "elevation_ft": 0,
          "heading_true": 311.1,
          "displaced_threshold_ft": 0
        }
      }
    }
  ],
  "frequencies": [
    {
      "type": "OTHER",
      "description": "HOUSTON CNTR",
      "mhz": 126.625
    }
  ],
  "metadata": {
    "ourairports_id": 9893,
    "created": "2026-03-06",
    "updated": "2026-03-06",
    "sources": [
      "ourairports",
      "faa"
    ]
  }
}