{
  "icao": null,
  "iata": null,
  "name": "Ottman Landing Airport",
  "type": "small_airport",
  "status": "open",
  "location": {
    "latitude": 44.594398498535156,
    "longitude": -92.25849914550781,
    "elevation_ft": 1150,
    "continent": "NA",
    "iso_country": "US",
    "iso_region": "US-WI",
    "municipality": "Maiden Rock"
  },
  "scheduled_service": false,
  "wikipedia": null,
  "keywords": [],
  "runways": [],
  "frequencies": [],
  "metadata": {
    "ourairports_id": 12742,
    "created": "2026-03-06",
    "updated": "2026-03-06",
    "sources": [
      "ourairports",
      "faa"
    ]
  }
}