{
  "key": "_ps_29928",
  "codes": {
    "icao": null,
    "iata": null,
    "gps": null,
    "local": null
  },
  "name": "Gush Katif Airport",
  "type": "closed",
  "status": "closed",
  "location": {
    "latitude": 31.36705,
    "longitude": 34.29451,
    "elevation_ft": 112,
    "iso_country": "PS",
    "iso_region": "PS-KYS",
    "municipality": "Khan Yunis"
  },
  "keywords": [
    "GHK",
    "Palestine",
    "Gaza",
    "LLAZ",
    "PS-0005"
  ],
  "wikipedia": "https://en.wikipedia.org/wiki/Gush_Katif",
  "metadata": {
    "created": "2026-06-21",
    "updated": "2026-06-21",
    "sources": [
      "ourairports"
    ],
    "curated": false,
    "source_id": 29928
  }
}
