{
  "key": "_fr_43551",
  "codes": {
    "icao": null,
    "iata": null,
    "gps": null,
    "local": null
  },
  "name": "Centre Hospitalier Heliport",
  "type": "heliport",
  "status": "open",
  "location": {
    "latitude": 45.564167,
    "longitude": 5.913333,
    "elevation_ft": 1047,
    "iso_country": "FR",
    "iso_region": "FR-ARA",
    "municipality": "Chambery"
  },
  "keywords": [
    "FR-0211"
  ],
  "metadata": {
    "created": "2026-06-21",
    "updated": "2026-06-21",
    "sources": [
      "ourairports"
    ],
    "curated": false,
    "source_id": 43551
  }
}
