{
  "key": "_ru_46345",
  "codes": {
    "icao": null,
    "iata": null,
    "gps": null,
    "local": null
  },
  "name": "Staritsa Airstrip",
  "type": "small_airport",
  "status": "open",
  "location": {
    "latitude": 56.512344,
    "longitude": 34.971972,
    "elevation_ft": 0,
    "iso_country": "RU",
    "iso_region": "RU-TVE",
    "municipality": "Staritsa"
  },
  "keywords": [
    "ВПП Старица",
    "RU-0420"
  ],
  "metadata": {
    "created": "2026-06-21",
    "updated": "2026-06-21",
    "sources": [
      "ourairports"
    ],
    "curated": false,
    "source_id": 46345
  }
}
