{
  "key": "kblh",
  "codes": {
    "icao": "KBLH",
    "iata": "BLH",
    "gps": "KBLH",
    "local": "BLH"
  },
  "name": "Blythe Airport",
  "type": "medium_airport",
  "status": "open",
  "location": {
    "latitude": 33.619202,
    "longitude": -114.717003,
    "elevation_ft": 399,
    "iso_country": "US",
    "iso_region": "US-CA",
    "municipality": "Blythe"
  },
  "keywords": [],
  "wikipedia": "https://en.wikipedia.org/wiki/Blythe_Airport",
  "metadata": {
    "created": "2026-06-21",
    "updated": "2026-06-21",
    "sources": [
      "ourairports"
    ],
    "curated": false,
    "source_id": 19388
  }
}
