{
  "key": "_us_571716",
  "codes": {
    "icao": null,
    "iata": null,
    "gps": null,
    "local": null
  },
  "name": "Grace Airport",
  "type": "closed",
  "status": "closed",
  "location": {
    "latitude": 33.24259,
    "longitude": -98.23761,
    "elevation_ft": 1066,
    "iso_country": "US",
    "iso_region": "US-TX",
    "municipality": "Jacksboro"
  },
  "keywords": [
    "Grace Landing Strip",
    "US-9238"
  ],
  "metadata": {
    "created": "2026-06-21",
    "updated": "2026-06-21",
    "sources": [
      "ourairports"
    ],
    "curated": false,
    "source_id": 571716
  }
}
