{
  "key": "_fr_528488",
  "codes": {
    "icao": null,
    "iata": null,
    "gps": null,
    "local": "LF4225"
  },
  "name": "Roanne Mably Airfield",
  "type": "small_airport",
  "status": "open",
  "location": {
    "latitude": 46.08561,
    "longitude": 4.086736,
    "elevation_ft": 895,
    "iso_country": "FR",
    "iso_region": "FR-ARA",
    "municipality": "Mably, Loire"
  },
  "keywords": [
    "Base ULM Roanne Mably",
    "FR-0589"
  ],
  "metadata": {
    "created": "2026-06-21",
    "updated": "2026-06-21",
    "sources": [
      "ourairports"
    ],
    "curated": false,
    "source_id": 528488
  }
}
