{
  "key": "_br_334935",
  "codes": {
    "icao": null,
    "iata": null,
    "gps": "SNJW",
    "local": "SP0881"
  },
  "name": "Cabletech Heliport",
  "type": "heliport",
  "status": "open",
  "location": {
    "latitude": -23.177677,
    "longitude": -45.726114,
    "elevation_ft": 2139,
    "iso_country": "BR",
    "iso_region": "BR-SP",
    "municipality": "Caçapava"
  },
  "keywords": [
    "BR-0692"
  ],
  "metadata": {
    "created": "2026-06-21",
    "updated": "2026-06-21",
    "sources": [
      "ourairports"
    ],
    "curated": false,
    "source_id": 334935
  }
}
