{
  "key": "_us_347549",
  "codes": {
    "icao": null,
    "iata": null,
    "gps": null,
    "local": null
  },
  "name": "Cohoe Airport",
  "type": "closed",
  "status": "closed",
  "location": {
    "latitude": 60.371548,
    "longitude": -151.306034,
    "elevation_ft": 55,
    "iso_country": "US",
    "iso_region": "US-AK",
    "municipality": "Cohoe"
  },
  "keywords": [
    "US-5117"
  ],
  "metadata": {
    "created": "2026-06-21",
    "updated": "2026-06-21",
    "sources": [
      "ourairports"
    ],
    "curated": false,
    "source_id": 347549
  }
}
