{
  "key": "_us_342375",
  "codes": {
    "icao": null,
    "iata": null,
    "gps": null,
    "local": null
  },
  "name": "Devil's Garden Airport",
  "type": "closed",
  "status": "closed",
  "location": {
    "latitude": 41.52174,
    "longitude": -120.66515,
    "elevation_ft": 4993,
    "iso_country": "US",
    "iso_region": "US-CA",
    "municipality": "Alturas"
  },
  "keywords": [
    "US-3363"
  ],
  "metadata": {
    "created": "2026-06-21",
    "updated": "2026-06-21",
    "sources": [
      "ourairports"
    ],
    "curated": false,
    "source_id": 342375
  }
}
