{
  "key": "_kz_351014",
  "codes": {
    "icao": null,
    "iata": null,
    "gps": null,
    "local": null
  },
  "name": "MCHS Heliport",
  "type": "heliport",
  "status": "open",
  "location": {
    "latitude": 43.10987,
    "longitude": 76.91634,
    "elevation_ft": 4777,
    "iso_country": "KZ",
    "iso_region": "KZ-ALA",
    "municipality": "Almaty"
  },
  "keywords": [
    "KZ-0119"
  ],
  "metadata": {
    "created": "2026-06-21",
    "updated": "2026-06-21",
    "sources": [
      "ourairports"
    ],
    "curated": false,
    "source_id": 351014
  }
}
