{
  "key": "_us_13224",
  "codes": {
    "icao": null,
    "iata": null,
    "gps": "6CO0",
    "local": "6CO0"
  },
  "name": "Doctors Mesa Airport",
  "type": "small_airport",
  "status": "open",
  "location": {
    "latitude": 38.852236,
    "longitude": -108.017833,
    "elevation_ft": 5680,
    "iso_country": "US",
    "iso_region": "US-CO",
    "municipality": "Eckert"
  },
  "keywords": [],
  "metadata": {
    "created": "2026-06-21",
    "updated": "2026-06-21",
    "sources": [
      "ourairports"
    ],
    "curated": false,
    "source_id": 13224
  }
}
