{
  "key": "_us_15646",
  "codes": {
    "icao": null,
    "iata": null,
    "gps": "9AK2",
    "local": "9AK2"
  },
  "name": "Kako Airport",
  "type": "small_airport",
  "status": "open",
  "location": {
    "latitude": 61.898899,
    "longitude": -161.438003,
    "elevation_ft": 300,
    "iso_country": "US",
    "iso_region": "US-AK",
    "municipality": "Russian Mission"
  },
  "keywords": [],
  "metadata": {
    "created": "2026-06-21",
    "updated": "2026-06-21",
    "sources": [
      "ourairports"
    ],
    "curated": false,
    "source_id": 15646
  }
}
