{
  "key": "_us_15487",
  "codes": {
    "icao": null,
    "iata": null,
    "gps": "96ID",
    "local": "96ID"
  },
  "name": "Flying H Ranch Airport",
  "type": "small_airport",
  "status": "open",
  "location": {
    "latitude": 48.235098,
    "longitude": -116.875634,
    "elevation_ft": 2230,
    "iso_country": "US",
    "iso_region": "US-ID",
    "municipality": "Priest River"
  },
  "keywords": [],
  "metadata": {
    "created": "2026-06-21",
    "updated": "2026-06-21",
    "sources": [
      "ourairports"
    ],
    "curated": false,
    "source_id": 15487
  }
}
