{
  "key": "_us_14161",
  "codes": {
    "icao": null,
    "iata": null,
    "gps": null,
    "local": null
  },
  "name": "Sills-Anderson Heliport",
  "type": "closed",
  "status": "closed",
  "location": {
    "latitude": 42.298599,
    "longitude": -89.2425,
    "elevation_ft": 950,
    "iso_country": "US",
    "iso_region": "US-IL",
    "municipality": "Winnebago"
  },
  "keywords": [
    "7IS1",
    "US-10716"
  ],
  "metadata": {
    "created": "2026-06-21",
    "updated": "2026-06-21",
    "sources": [
      "ourairports"
    ],
    "curated": false,
    "source_id": 14161
  }
}
