{
  "key": "_mx_318879",
  "codes": {
    "icao": null,
    "iata": null,
    "gps": null,
    "local": "LUA"
  },
  "name": "La Burra Airport",
  "type": "small_airport",
  "status": "open",
  "location": {
    "latitude": 28.06394,
    "longitude": -100.16332,
    "elevation_ft": 700,
    "iso_country": "MX",
    "iso_region": "MX-COA",
    "municipality": "Guerrero"
  },
  "keywords": [
    "MX-0150"
  ],
  "metadata": {
    "created": "2026-06-21",
    "updated": "2026-06-21",
    "sources": [
      "ourairports"
    ],
    "curated": false,
    "source_id": 318879
  }
}
