{
  "key": "_tz_42495",
  "codes": {
    "icao": null,
    "iata": null,
    "gps": null,
    "local": null
  },
  "name": "Mbinga Airport",
  "type": "small_airport",
  "status": "open",
  "location": {
    "latitude": -10.964,
    "longitude": 35.011799,
    "elevation_ft": 4335,
    "iso_country": "TZ",
    "iso_region": "TZ-21",
    "municipality": "Mbinga"
  },
  "keywords": [
    "TZ-0003"
  ],
  "metadata": {
    "created": "2026-06-21",
    "updated": "2026-06-21",
    "sources": [
      "ourairports"
    ],
    "curated": false,
    "source_id": 42495
  }
}
