{
  "key": "_us_18920",
  "codes": {
    "icao": null,
    "iata": null,
    "gps": "K5R1",
    "local": "5R1"
  },
  "name": "Roy Wilcox Airport",
  "type": "small_airport",
  "status": "open",
  "location": {
    "latitude": 31.451799,
    "longitude": -88.194504,
    "elevation_ft": 165,
    "iso_country": "US",
    "iso_region": "US-AL",
    "municipality": "Chatom"
  },
  "keywords": [],
  "wikipedia": "https://en.wikipedia.org/wiki/Roy_Wilcox_Airport",
  "metadata": {
    "created": "2026-06-21",
    "updated": "2026-06-21",
    "sources": [
      "ourairports"
    ],
    "curated": false,
    "source_id": 18920
  }
}
