{
  "key": "_vn_430108",
  "codes": {
    "icao": null,
    "iata": null,
    "gps": null,
    "local": null
  },
  "name": "Can Tho Army Airfield",
  "type": "closed",
  "status": "closed",
  "location": {
    "latitude": 10.05125,
    "longitude": 105.76271,
    "elevation_ft": 7,
    "iso_country": "VN",
    "iso_region": "VN-SW",
    "municipality": "Can Tho"
  },
  "keywords": [
    "VN-0048"
  ],
  "metadata": {
    "created": "2026-06-21",
    "updated": "2026-06-21",
    "sources": [
      "ourairports"
    ],
    "curated": false,
    "source_id": 430108
  }
}
